pygame_exp/__init__.py
pygame_exp/game_math.py
pygame_exp/main.py
PygameExp-1.0.3.dist-info/METADATA
PygameExp-1.0.3.dist-info/WHEEL
PygameExp-1.0.3.dist-info/top_level.txt
PygameExp-1.0.3.dist-info/RECORD
