Metadata-Version: 2.1
Name: PygameExp
Version: 1.0.3
Requires-Dist: pygame
